{
  "kind": "collectionType",
  "collectionName": "posts",
  "info": {
    "singularName": "post",
    "pluralName": "posts",
    "displayName": "post"
  },
  "options": {
    "draftAndPublish": false
  },
  "attributes": {
    "title": {
      "type": "string",
      "required": true
    },
    "slug": {
      "type": "uid",
      "targetField": "title",
      "required": true,
      "unique": true
    },
    "excerpt": {
      "type": "text"
    },
    "status": {
      "type": "enumeration",
      "enum": [
        "draft",
        "published"
      ],
      "default": "draft"
    },
    "publishedAt": {
      "type": "datetime"
    },
    "coverImage": {
      "type": "media",
      "multiple": false,
      "allowedTypes": [
        "images"
      ]
    },
    "category": {
      "type": "relation",
      "relation": "manyToOne",
      "target": "api::category.category"
    },
    "tags": {
      "type": "relation",
      "relation": "manyToMany",
      "target": "api::tag.tag"
    },
    "contentHtml": {
      "type": "text",
      "required": true
    },
    "seo": {
      "type": "component",
      "component": "shared.seo",
      "repeatable": false
    }
  }
}
